qbraid_cli/__init__.py
qbraid_cli/_version.py
qbraid_cli/exceptions.py
qbraid_cli/handlers.py
qbraid_cli/main.py
qbraid_cli/py.typed
qbraid_cli/account/__init__.py
qbraid_cli/account/app.py
qbraid_cli/admin/__init__.py
qbraid_cli/admin/app.py
qbraid_cli/admin/headers.py
qbraid_cli/admin/validation.py
qbraid_cli/chat/__init__.py
qbraid_cli/chat/app.py
qbraid_cli/configure/__init__.py
qbraid_cli/configure/actions.py
qbraid_cli/configure/app.py
qbraid_cli/configure/claude_config.py
qbraid_cli/devices/__init__.py
qbraid_cli/devices/app.py
qbraid_cli/devices/validation.py
qbraid_cli/envs/__init__.py
qbraid_cli/envs/activate.py
qbraid_cli/envs/app.py
qbraid_cli/envs/create.py
qbraid_cli/envs/data_handling.py
qbraid_cli/files/__init__.py
qbraid_cli/files/app.py
qbraid_cli/jobs/__init__.py
qbraid_cli/jobs/app.py
qbraid_cli/jobs/toggle_braket.py
qbraid_cli/jobs/validation.py
qbraid_cli/kernels/__init__.py
qbraid_cli/kernels/app.py
qbraid_cli/mcp/__init__.py
qbraid_cli/mcp/app.py
qbraid_cli/mcp/serve.py
qbraid_cli/pip/__init__.py
qbraid_cli/pip/app.py
qbraid_cli/pip/hooks.py
qbraid_cli-0.11.0.dist-info/licenses/LICENSE
qbraid_cli-0.11.0.dist-info/METADATA
qbraid_cli-0.11.0.dist-info/WHEEL
qbraid_cli-0.11.0.dist-info/entry_points.txt
qbraid_cli-0.11.0.dist-info/top_level.txt
qbraid_cli-0.11.0.dist-info/RECORD
