Metadata-Version: 2.4
Name: qbraid-cli
Version: 0.11.0
Summary: Command Line Interface for interacting with all parts of the qBraid platform.
Author-email: qBraid Development Team <contact@qbraid.com>
License-Expression: LicenseRef-Proprietary
Project-URL: Homepage, https://docs.qbraid.com/cli/user-guide/overview
Project-URL: Documentation, https://docs.qbraid.com/cli/api-reference/qbraid
Project-URL: Bug Tracker, https://github.com/qBraid/community/issues
Project-URL: Discord, https://discord.gg/KugF6Cnncm
Keywords: qbraid,cli,quantum,cloud
Classifier: Development Status :: 5 - Production/Stable
Classifier: Intended Audience :: Developers
Classifier: Natural Language :: English
Classifier: Intended Audience :: System Administrators
Classifier: Operating System :: Microsoft :: Windows
Classifier: Operating System :: POSIX :: Linux
Classifier: Programming Language :: Python
Classifier: Programming Language :: Python :: 3
Classifier: Programming Language :: Python :: 3 :: Only
Classifier: Programming Language :: Python :: 3.9
Classifier: Programming Language :: Python :: 3.10
Classifier: Programming Language :: Python :: 3.11
Classifier: Programming Language :: Python :: 3.12
Classifier: Programming Language :: Python :: 3.13
Requires-Python: >=3.9
License-File: LICENSE
Requires-Dist: typer>=0.12.1
Requires-Dist: rich>=10.11.0
Requires-Dist: click<=8.1.8
Requires-Dist: qbraid-core<0.2,>=0.1.45
Provides-Extra: jobs
Requires-Dist: amazon-braket-sdk>=1.48.1; extra == "jobs"
Provides-Extra: envs
Requires-Dist: qbraid-core[environments]<0.2,>=0.1.42; extra == "envs"
Provides-Extra: mcp
Requires-Dist: qbraid-core[mcp]<0.2,>=0.1.45; extra == "mcp"
Provides-Extra: dev
Requires-Dist: isort; extra == "dev"
Requires-Dist: black; extra == "dev"
Requires-Dist: pytest; extra == "dev"
Requires-Dist: pytest-cov; extra == "dev"
Requires-Dist: pytest-asyncio; extra == "dev"
Dynamic: license-file
